djclient/__init__.py
djclient/dj.py
djclient/exceptions.py
djclient-0.0.1a3.dist-info/LICENSE.txt
djclient-0.0.1a3.dist-info/METADATA
djclient-0.0.1a3.dist-info/WHEEL
djclient-0.0.1a3.dist-info/RECORD
