Metadata-Version: 2.1
Name: djclient
Version: 0.0.1a3
Summary: DataJunction client library for connecting to a DataJunction server
Home-page: https://github.com/DataJunction/dj
License: MIT
Author: DataJunction Authors
Requires-Python: >=3.8,<4.0
Classifier: License :: OSI Approved :: MIT License
Classifier: Operating System :: OS Independent
Classifier: Programming Language :: Python :: 3
Classifier: Programming Language :: Python :: 3.8
Classifier: Programming Language :: Python :: 3.9
Classifier: Programming Language :: Python :: 3.10
Classifier: Programming Language :: Python :: 3.11
Classifier: Programming Language :: Python :: 3.10
Classifier: Programming Language :: Python :: 3.11
Classifier: Programming Language :: Python :: 3.12
Classifier: Programming Language :: Python :: 3.8
Classifier: Programming Language :: Python :: 3.9
Requires-Dist: pandas (>=2)
Requires-Dist: pydantic (>=1)
Project-URL: Repository, https://github.com/DataJunction/dj
